Eva/__init__.py
Eva/eva.py
Eva/status.py
eva_lcd-0.1.1.dist-info/LICENSE
eva_lcd-0.1.1.dist-info/METADATA
eva_lcd-0.1.1.dist-info/WHEEL
eva_lcd-0.1.1.dist-info/top_level.txt
eva_lcd-0.1.1.dist-info/RECORD
